emr_cli/config.py
emr_cli/deployments/__init__.py
emr_cli/deployments/emr_ec2.py
emr_cli/deployments/emr_eks.py
emr_cli/deployments/emr_serverless.py
emr_cli/emr_cli.py
emr_cli/packaging/detector.py
emr_cli/packaging/python_files_project.py
emr_cli/packaging/python_poetry_project.py
emr_cli/packaging/python_project.py
emr_cli/packaging/simple_project.py
emr_cli/templates/poetry/README.md
emr_cli/templates/poetry/pyproject.toml
emr_cli/templates/pyspark/.dockerignore
emr_cli/templates/pyspark/.gitignore
emr_cli/templates/pyspark/Dockerfile
emr_cli/templates/pyspark/entrypoint.py
emr_cli/templates/pyspark/jobs/extreme_weather.py
emr_cli/templates/pyspark/pyproject.toml
emr_cli/utils/__init__.py
emr_cli-0.0.19.dist-info/LICENSE
emr_cli-0.0.19.dist-info/METADATA
emr_cli-0.0.19.dist-info/NOTICE
emr_cli-0.0.19.dist-info/WHEEL
emr_cli-0.0.19.dist-info/entry_points.txt
emr_cli-0.0.19.dist-info/RECORD
