Metadata-Version: 2.1
Name: emr-cli
Version: 0.0.19
Summary: A command-line interface for packaging, deploying, and running your PySpark jobs on EMR.
License: Apache-2.0
Author: Amazon EMR
Author-email: emr-developer-advocates@amazon.com
Requires-Python: >=3.7,<4.0
Classifier: License :: OSI Approved :: Apache Software License
Classifier: Programming Language :: Python :: 3
Classifier: Programming Language :: Python :: 3.7
Classifier: Programming Language :: Python :: 3.8
Classifier: Programming Language :: Python :: 3.9
Classifier: Programming Language :: Python :: 3.10
Classifier: Programming Language :: Python :: 3.11
Classifier: Programming Language :: Python :: 3.12
Requires-Dist: boto3 (>=1.26.6,<2.0.0)
Requires-Dist: click (>=7.1.2,<8.0.0)
Requires-Dist: importlib-metadata (==6.7.0) ; python_version == "3.7"
Requires-Dist: pyyaml (==5.3.1)
Requires-Dist: rich (>=13.4.2,<14.0.0)
